[
    {
        "title": "Densetsu Kyojin Ideon",
        "livechart": "5423",
        "mal": "930",
        "_key": "5423"
    },
    {
        "title": "Terra e...",
        "livechart": "6147",
        "mal": "2560",
        "_key": "6147"
    },
    {
        "title": "Ashita no Joe (Movie)",
        "livechart": "6716",
        "mal": "2920",
        "_key": "6716"
    },
    {
        "title": "Doraemon Movie 01: Nobita no Kyouryuu",
        "livechart": "6880",
        "mal": "3727",
        "_key": "6880"
    },
    {
        "title": "Ie Naki Ko (Movie)",
        "livechart": "7025",
        "mal": "2831",
        "_key": "7025"
    },
    {
        "title": "Wakakusa Monogatari",
        "livechart": "7660",
        "mal": "4991",
        "_key": "7660"
    },
    {
        "title": "Sekai Meisaku Douwa: Mori wa Ikiteiru",
        "livechart": "7868",
        "mal": "3751",
        "_key": "7868"
    },
    {
        "title": "Tsurikichi Sanpei",
        "livechart": "8252",
        "mal": "3137",
        "_key": "8252"
    },
    {
        "title": "Ginga Tetsudou 999: Glass no Clair",
        "livechart": "8596",
        "mal": "6653",
        "_key": "8596"
    },
    {
        "title": "Captain",
        "livechart": "11315",
        "mal": "27915",
        "_key": "11315"
    }
]